s3_cas/__init__.py
s3_cas-1.0.0.dist-info/LICENSE
s3_cas-1.0.0.dist-info/METADATA
s3_cas-1.0.0.dist-info/WHEEL
s3_cas-1.0.0.dist-info/top_level.txt
s3_cas-1.0.0.dist-info/RECORD
