Metadata-Version: 2.1
Name: s3-cas
Version: 1.0.0
Summary: S3 Content-Addressable Storage
Home-page: https://github.com/nuchi/s3-cas
Author: Haggai Nuchi
Author-email: haggai@haggainuchi.com
License: MIT
Keywords: aws,botocore,boto3,s3
Platform: any
License-File: LICENSE
Requires-Dist: boto3 (>=1.0)
Requires-Dist: botocore (>=1.0)
